queryshield_core/__init__.py
queryshield_core/budgets.py
queryshield_core/utils.py
queryshield_core/analysis/__init__.py
queryshield_core/analysis/classify.py
queryshield_core/analysis/explain_checks.py
queryshield_core/analysis/ml_suggestions.py
queryshield_core-0.2.0.dist-info/METADATA
queryshield_core-0.2.0.dist-info/WHEEL
queryshield_core-0.2.0.dist-info/RECORD
