Metadata-Version: 2.4
Name: queryshield-core
Version: 0.2.0
Summary: QueryShield core analysis library - shared logic for all probe packages
Project-URL: Homepage, https://queryshield.io
Project-URL: Repository, https://github.com/queryshield/queryshield
Author-email: QueryShield <dev@queryshield.io>
Requires-Python: >=3.9
Requires-Dist: pyyaml>=6.0
Provides-Extra: dev
Requires-Dist: pytest-cov>=4.1.0; extra == 'dev'
Requires-Dist: pytest>=7.4.0; extra == 'dev'
